{
    "frames": [
        {
            "filename": "idle1",
            "frame": {
            "x": 82,
            "y": 55,
            "w": 57,
            "h": 86
            },
            "anchor": {
                "x": 0.5,
                "y": 0.5
            }
        },
        {
            "filename": "idle2",
            "frame": {
            "x": 313,
            "y": 55,
            "w": 57,
            "h": 86
            },
            "anchor": {
                "x": 0.5,
                "y": 0.5
            }
        },
        {
            "filename": "idle3",
            "frame": {
            "x": 544,
            "y": 55,
            "w": 57,
            "h": 86
            },
            "anchor": {
                "x": 0.5,
                "y": 0.5
            }
        },
        {
            "filename": "idle4",
            "frame": {
            "x": 775,
            "y": 55,
            "w": 57,
            "h": 86
            },
            "anchor": {
                "x": 0.5,
                "y": 0.5
            }
        },
        {
            "filename": "idle5",
            "frame": {
            "x": 1006,
            "y": 55,
            "w": 57,
            "h": 86
            },
            "anchor": {
                "x": 0.5,
                "y": 0.5
            }
        },
        {
            "filename": "idle6",
            "frame": {
            "x": 1237,
            "y": 55,
            "w": 57,
            "h": 86
            },
            "anchor": {
                "x": 0.5,
                "y": 0.5
            }
            
        }
    ]
}